pyresidfp/__init__.py
pyresidfp/_pyresidfp.cpython-314t-aarch64-linux-musl.so
pyresidfp/_pyresidfp.pyi
pyresidfp/_version.py
pyresidfp/musical_scale.py
pyresidfp/py.typed
pyresidfp/registers.py
pyresidfp/sound_interface_device.py
pyresidfp.libs/libgcc_s-2d945d6c.so.1
pyresidfp.libs/libstdc++-85f2cd6d.so.6.0.33
pyresidfp-0.17.0.dist-info/METADATA
pyresidfp-0.17.0.dist-info/WHEEL
pyresidfp-0.17.0.dist-info/RECORD
pyresidfp-0.17.0.dist-info/licenses/COPYING
