Metadata-Version: 2.1
Name: pyresidfp
Version: 0.17.0
Summary: Emulates the SID sound-chip
Author-Email: Sebastian Klemke <pypi@nerdheim.de>
Classifier: Programming Language :: Python :: 3
Classifier: Programming Language :: Python :: 3.10
Classifier: Programming Language :: Python :: 3.11
Classifier: Programming Language :: Python :: 3.12
Classifier: Programming Language :: Python :: 3.13
Classifier: Programming Language :: Python :: 3.14
Classifier: Programming Language :: Python :: 3 :: Only
Classifier: Programming Language :: C++
Classifier: License :: OSI Approved :: GNU General Public License v2 or later (GPLv2+)
Classifier: Operating System :: OS Independent
Classifier: Topic :: Multimedia :: Sound/Audio :: Sound Synthesis
Classifier: Topic :: System :: Emulators
Classifier: Intended Audience :: Developers
Classifier: Development Status :: 2 - Pre-Alpha
Project-URL: Homepage, https://github.com/pyresidfp/pyresidfp
Project-URL: Bug Tracker, https://github.com/pyresidfp/pyresidfp/issues
Requires-Python: <4.0.0,>=3.10.0
